tcn/__init__.py
tcn/tcn.py
keras_tcn_macos-1.0.dist-info/LICENSE
keras_tcn_macos-1.0.dist-info/METADATA
keras_tcn_macos-1.0.dist-info/WHEEL
keras_tcn_macos-1.0.dist-info/top_level.txt
keras_tcn_macos-1.0.dist-info/RECORD
