Metadata-Version: 2.1
Name: keras-tcn-macos
Version: 1.0
Summary: Keras TCN (macOS)
Author: Philippe Remy
License: MIT
Platform: UNKNOWN
License-File: LICENSE
Requires-Dist: numpy
Requires-Dist: tensorflow-macos
Requires-Dist: tensorflow-addons
